slideslurper/__init__.py
slideslurper-2.0.0.dist-info/METADATA
slideslurper-2.0.0.dist-info/WHEEL
slideslurper-2.0.0.dist-info/entry_points.txt
slideslurper-2.0.0.dist-info/RECORD
