Metadata-Version: 2.4
Name: slideslurper
Version: 2.0.0
Summary: slurp slides from lecture videos
Project-URL: repository, https://github.com/vkorelsky/slideSlurper
Author-email: Victor Korelsky <VKorelsky@users.noreply.github.com>
License-Expression: MIT
Keywords: capture,lectures,video
Requires-Python: >=3.13
Requires-Dist: fpdf>=1.7.2
Requires-Dist: numpy>=2.3.0
Requires-Dist: opencv-python>=4.11.0.86
Requires-Dist: tqdm>=4.67.1
